earthkit/regrid/__init__.py
earthkit/regrid/_version.py
earthkit/regrid/db.py
earthkit/regrid/gridspec.py
earthkit/regrid/interpolate.py
earthkit/regrid/sphinxext/__init__.py
earthkit/regrid/sphinxext/generate_inventory_rst.py
earthkit/regrid/sphinxext/module_output.py
earthkit/regrid/sphinxext/xref.py
earthkit/regrid/utils/__init__.py
earthkit/regrid/utils/caching.py
earthkit/regrid/utils/download.py
earthkit/regrid/utils/hash.py
earthkit/regrid/utils/humanize.py
earthkit/regrid/utils/matrix.py
earthkit/regrid/utils/memcache.py
earthkit/regrid/utils/mir.py
earthkit/regrid/utils/stream.py
earthkit/regrid/utils/temporary.py
earthkit_regrid-0.4.2.dist-info/METADATA
earthkit_regrid-0.4.2.dist-info/WHEEL
earthkit_regrid-0.4.2.dist-info/top_level.txt
earthkit_regrid-0.4.2.dist-info/RECORD
