Metadata-Version: 2.4
Name: earthkit-regrid
Version: 0.4.2
Summary: ECMWF python regridding toolkit
Author-email: "European Centre for Medium-Range Weather Forecasts (ECMWF)" <software.support@ecmwf.int>
License: Apache License Version 2.0
Project-URL: Documentation, https://earthkit-regrid.readthedocs.io/
Project-URL: Homepage, https://github.com/ecmwf/earthkit-regrid/
Project-URL: Issues, https://github.com/ecmwf/earthkit-regrid.issues
Project-URL: Repository, https://github.com/ecmwf/earthkit-regrid/
Classifier: Development Status :: 2 - Pre-Alpha
Classifier: Intended Audience :: Developers
Classifier: License :: OSI Approved :: Apache Software License
Classifier: Programming Language :: Python :: 3
Classifier: Programming Language :: Python :: 3.8
Classifier: Programming Language :: Python :: 3.9
Classifier: Programming Language :: Python :: 3.10
Classifier: Programming Language :: Python :: 3.11
Classifier: Programming Language :: Python :: Implementation :: CPython
Classifier: Programming Language :: Python :: Implementation :: PyPy
Classifier: Operating System :: OS Independent
Requires-Python: >=3.8
Requires-Dist: multiurl
Requires-Dist: filelock
Requires-Dist: scipy
Provides-Extra: test
Requires-Dist: pytest; extra == "test"
Requires-Dist: pytest-cov; extra == "test"
Requires-Dist: requests; extra == "test"
